Aciembler/Aciembler.py
Aciembler/Error.py
Aciembler/First_pass.py
Aciembler/__init__.py
Aciembler/objectCode.py
Aciembler/translator.py
Aciembler-2.0.1.dist-info/LICENSE.txt
Aciembler-2.0.1.dist-info/METADATA
Aciembler-2.0.1.dist-info/WHEEL
Aciembler-2.0.1.dist-info/top_level.txt
Aciembler-2.0.1.dist-info/RECORD
