Metadata-Version: 2.1
Name: Aciembler
Version: 2.0.1
Summary: A CAIE 9618 assembler
Author: hhaolin, AY
Author-email: 2813579566@qq.com, Andrewsly@163.com
License: MIT
Keywords: CAIE,9618,Assembler
Platform: all
Classifier: Intended Audience :: Developers
Classifier: Operating System :: OS Independent
Classifier: Natural Language :: Chinese (Simplified)
Classifier: Programming Language :: Python :: 3.10
Classifier: Programming Language :: Python :: 3.11
Classifier: Programming Language :: Python :: 3.12
Classifier: Topic :: Software Development :: Libraries
License-File: LICENSE.txt
Requires-Dist: HHLtools (>=1.2.1)
Requires-Dist: tabulate
Requires-Dist: xlrd2
